tkpysdk/__init__.py
tkpysdk/utils/__init__.py
tkpysdk/utils/config.py
tkpysdk/utils/network.py
tkpysdk/utils/order_utils.py
tkpysdk/utils/position_utils.py
tkpysdk/utils/quote_utils.py
tkpysdk/utils/shared_utils.py
tkpysdk/utils/signature.py
tkpysdk/utils/swap_utils.py
tkpysdk-0.0.1.dist-info/METADATA
tkpysdk-0.0.1.dist-info/WHEEL
tkpysdk-0.0.1.dist-info/top_level.txt
tkpysdk-0.0.1.dist-info/RECORD
