Metadata-Version: 2.1
Name: tkpysdk
Version: 0.0.1
Summary: 300k sdk for python
Home-page: UNKNOWN
Author: Hao W
Author-email: UNKNOWN
License: Copyright 2023, 300k ltd, All rights reserved
Platform: UNKNOWN
Classifier: Development Status :: 3 - Alpha
Classifier: Intended Audience :: Developers
Classifier: License :: OSI Approved :: MIT License
Classifier: Programming Language :: Python :: 3
